sync_conflict/__init__.py
sync_conflict/commands.py
sync_conflict/utils.py
sync_conflict-0.2.0.dist-info/LICENSE
sync_conflict-0.2.0.dist-info/METADATA
sync_conflict-0.2.0.dist-info/WHEEL
sync_conflict-0.2.0.dist-info/entry_points.txt
sync_conflict-0.2.0.dist-info/top_level.txt
sync_conflict-0.2.0.dist-info/RECORD
