Metadata-Version: 2.1
Name: sync_conflict
Version: 0.2.0
Summary: Search conflict file generated by syncthing
Home-page: https://github.com/ritonun/sync_conflict
Keywords: syncthing,cli
Classifier: License :: OSI Approved :: MIT License
Classifier: Programming Language :: Python :: 3 :: Only
Requires-Python: >=3.7, <4
License-File: LICENSE
Requires-Dist: Click
